model_harmonics/__init__.py
model_harmonics/datum.py
model_harmonics/gen_atmosphere_stokes.py
model_harmonics/gen_point_pressure.py
model_harmonics/gen_pressure_stokes.py
model_harmonics/greens_kernel.py
model_harmonics/spatial.py
model_harmonics/utilities.py
model_harmonics/version.py
model_harmonics-1.1.2.data/scripts/GIA_GSFC_mascons.py
model_harmonics-1.1.2.data/scripts/GIA_spatial_maps.py
model_harmonics-1.1.2.data/scripts/GIA_uplift_ICESat2_ATL15.py
model_harmonics-1.1.2.data/scripts/cds_land_retrieve.py
model_harmonics-1.1.2.data/scripts/cds_reanalysis_retrieve.py
model_harmonics-1.1.2.data/scripts/ecco_depth_version4.py
model_harmonics-1.1.2.data/scripts/ecco_geoid_llc_tiles.py
model_harmonics-1.1.2.data/scripts/ecco_llc_tile_harmonics.py
model_harmonics-1.1.2.data/scripts/ecco_mean_llc_tiles.py
model_harmonics-1.1.2.data/scripts/ecco_mean_realtime.py
model_harmonics-1.1.2.data/scripts/ecco_mean_version4.py
model_harmonics-1.1.2.data/scripts/ecco_monthly_harmonics.py
model_harmonics-1.1.2.data/scripts/ecco_read_llc_tiles.py
model_harmonics-1.1.2.data/scripts/ecco_read_realtime.py
model_harmonics-1.1.2.data/scripts/ecco_read_version4.py
model_harmonics-1.1.2.data/scripts/ecmwf_reanalysis_retrieve.py
model_harmonics-1.1.2.data/scripts/era5_land_mask_arctic.py
model_harmonics-1.1.2.data/scripts/era5_land_mask_permafrost.py
model_harmonics-1.1.2.data/scripts/era5_land_mean_monthly.py
model_harmonics-1.1.2.data/scripts/era5_land_monthly_harmonics.py
model_harmonics-1.1.2.data/scripts/era5_land_read_monthly.py
model_harmonics-1.1.2.data/scripts/era5_smb_cumulative.py
model_harmonics-1.1.2.data/scripts/era5_smb_harmonics.py
model_harmonics-1.1.2.data/scripts/era5_smb_mean.py
model_harmonics-1.1.2.data/scripts/gemb_smb_cumulative.py
model_harmonics-1.1.2.data/scripts/gemb_smb_harmonics.py
model_harmonics-1.1.2.data/scripts/gesdisc_gldas_sync.py
model_harmonics-1.1.2.data/scripts/gesdisc_merra_download.py
model_harmonics-1.1.2.data/scripts/gesdisc_merra_monthly.py
model_harmonics-1.1.2.dist-info/licenses/LICENSE
model_harmonics-1.1.2.dist-info/METADATA
model_harmonics-1.1.2.dist-info/WHEEL
model_harmonics-1.1.2.dist-info/top_level.txt
model_harmonics-1.1.2.dist-info/RECORD
