Metadata-Version: 2.4
Name: model-harmonics
Version: 1.1.2
Summary: Python tools for obtaining and working with model synthetic spherical harmonic coefficients for comparing with data from the NASA/DLR GRACE and NASA/GFZ GRACE Follow-on missions
Home-page: https://github.com/tsutterley/model-harmonics
Author: Tyler Sutterley
Author-email: tsutterl@uw.edu
License: MIT
Keywords: gravity synthetics,physical geodesy,spherical harmonics
Classifier: Development Status :: 3 - Alpha
Classifier: Intended Audience :: Science/Research
Classifier: Topic :: Scientific/Engineering :: Physics
Classifier: License :: OSI Approved :: MIT License
Classifier: Programming Language :: Python :: 3
Classifier: Programming Language :: Python :: 3.5
Classifier: Programming Language :: Python :: 3.6
Classifier: Programming Language :: Python :: 3.7
Classifier: Programming Language :: Python :: 3.8
License-File: LICENSE
Requires-Dist: cdsapi
Requires-Dist: ecmwf-api-client
Requires-Dist: fiona
Requires-Dist: geoid-toolkit
Requires-Dist: gravity-toolkit
Requires-Dist: pyproj
Requires-Dist: shapely
Requires-Dist: scikit-learn
Dynamic: author
Dynamic: author-email
Dynamic: classifier
Dynamic: description
Dynamic: description-content-type
Dynamic: home-page
Dynamic: keywords
Dynamic: license
Dynamic: license-file
Dynamic: requires-dist
Dynamic: summary
